dharmamitra_sanskrit_grammar/__init__.py
dharmamitra_sanskrit_grammar/processor.py
dharmamitra_sanskrit_grammar-0.1.7.dist-info/LICENSE
dharmamitra_sanskrit_grammar-0.1.7.dist-info/METADATA
dharmamitra_sanskrit_grammar-0.1.7.dist-info/WHEEL
dharmamitra_sanskrit_grammar-0.1.7.dist-info/top_level.txt
dharmamitra_sanskrit_grammar-0.1.7.dist-info/RECORD
