Metadata-Version: 2.1
Name: dharmamitra-sanskrit-grammar
Version: 0.1.7
Summary: Sanskrit grammar processing using the Dharmamitra API
Author: dharmamitra
Requires-Python: >=3.7
License-File: LICENSE
Requires-Dist: requests>=2.25.0
